ex1.v
module ex1(J,K,CK,PR,CLR,Q);

    input J, K, CK, PR, CLR;
    output reg Q;

    always @(posedge CK) begin
        if (PR == 1'b1 && CLR == 1'b0)
            Q = 1'b0;
        else if (PR == 1'b0 && CLR == 1'b1)
            Q = 1'b1;
        else if (PR == 1'b0 && CLR == 1'b0)
            Q = 1'bx;
        else begin
            case({J, K})//PARA CONCATENAR
                2'b00: Q = Q;
                2'b01: Q = 1'b0;
                2'b10: Q = 1'b1;
                2'b11: Q = ~Q;
            endcase
        end
    end
endmodule

ex1/ex1_tb.v
`timescale 1ns/1ns
`include "ex1.v"

module ex1_tb;

    reg J, K, CK, PR, CLR;
    wire Q;

    ex1 uut(J, K, CK, PR, CLR, Q);

    initial begin
            $dumpfile ("ex1.vcd");
            $dumpvars (1) ;

            PR = 1; CLR = 0; #20;
            PR = 1; CLR = 1; J = 0; K = 0; #20;
            J = 0; K = 1; #20;
            J = 1; K = 0; #20;
            J = 1; K = 1; #20;
            $finish ;
        end

        initial begin
            CK = 0;
            forever #10 CK = ~ CK;
        end
endmodule

ex1.vcd
$date
	Mon Oct 21 10:55:58 2024
$end
$version
	Icarus Verilog
$end
$timescale
	1ns
$end
$scope module ex1_tb $end
$var wire 1 ! Q $end
$var reg 1 " CK $end
$var reg 1 # CLR $end
$var reg 1 $ J $end
$var reg 1 % K $end
$var reg 1 & PR $end
$upscope $end
$enddefinitions $end
$comment Show the parameter values. $end
$dumpall
$end
#0
$dumpvars
1&
x%
x$
0#
0"
x!
$end
#10
0!
1"
#20
0"
0%
0$
1#
#30
1"
#40
0"
1%
#50
1"
#60
0"
0%
1$
#70
1!
1"
#80
0"
1%
#90
0!
1"
